fgsmk/__init__.py
fgsmk/io.py
fgsmk/log.py
fgsmk/py.typed
fgsmk/testing.py
fgsmk-0.1.1.dist-info/LICENSE
fgsmk-0.1.1.dist-info/METADATA
fgsmk-0.1.1.dist-info/WHEEL
fgsmk-0.1.1.dist-info/RECORD
