Metadata-Version: 2.3
Name: fgsmk
Version: 0.1.1
Summary: Supporting functions for running Snakemake workflows.
License: MIT
Author: Fulcrum Genomics LLC
Author-email: contact@fulcrumgenomics.com
Requires-Python: >=3.11.0,<3.13
Classifier: Development Status :: 3 - Alpha
Classifier: License :: OSI Approved :: MIT License
Classifier: Programming Language :: Python :: 3
Classifier: Programming Language :: Python :: 3.11
Classifier: Programming Language :: Python :: 3.12
Requires-Dist: fgpyo (==1.0.0)
Requires-Dist: snakemake (>=8.27.1,<9.0.0)
Project-URL: Bug Tracker, https://github.com/fulcrumgenomics/fgsmk/issues
Project-URL: Documentation, https://github.com/fulcrumgenomics/fgsmk
Project-URL: Homepage, https://github.com/fulcrumgenomics/fgsmk
Project-URL: Repository, https://github.com/fulcrumgenomics/fgsmk
